combocurve_api_helper/__init__.py
combocurve_api_helper/base.py
combocurve_api_helper/company_models.py
combocurve_api_helper/config.py
combocurve_api_helper/directional.py
combocurve_api_helper/econ_runs.py
combocurve_api_helper/forecasts.py
combocurve_api_helper/models.py
combocurve_api_helper/production.py
combocurve_api_helper/projects.py
combocurve_api_helper/py.typed
combocurve_api_helper/root.py
combocurve_api_helper/scenarios.py
combocurve_api_helper/test_api.py
combocurve_api_helper/typecurves.py
combocurve_api_helper/wells.py
combocurve_api_helper/__pycache__/__init__.cpython-310.pyc
combocurve_api_helper/__pycache__/base.cpython-310.pyc
combocurve_api_helper/__pycache__/company_models.cpython-310.pyc
combocurve_api_helper/__pycache__/config.cpython-310.pyc
combocurve_api_helper/__pycache__/directional.cpython-310.pyc
combocurve_api_helper/__pycache__/econ_runs.cpython-310.pyc
combocurve_api_helper/__pycache__/forecasts.cpython-310.pyc
combocurve_api_helper/__pycache__/models.cpython-310.pyc
combocurve_api_helper/__pycache__/production.cpython-310.pyc
combocurve_api_helper/__pycache__/projects.cpython-310.pyc
combocurve_api_helper/__pycache__/root.cpython-310.pyc
combocurve_api_helper/__pycache__/scenarios.cpython-310.pyc
combocurve_api_helper/__pycache__/typecurves.cpython-310.pyc
combocurve_api_helper/__pycache__/wells.cpython-310.pyc
combocurve_api_helper/assets/econModels.json
combocurve_api_helper/assets/wellHeader.json
combocurve_api_helper-1.2.0.dist-info/licenses/LICENSE
combocurve_api_helper-1.2.0.dist-info/METADATA
combocurve_api_helper-1.2.0.dist-info/WHEEL
combocurve_api_helper-1.2.0.dist-info/top_level.txt
combocurve_api_helper-1.2.0.dist-info/RECORD
