Metadata-Version: 2.4
Name: combocurve-api-helper
Version: 1.2.0
Summary: A library mapped to ComboCurve's API.
Author: David S. Fulford
Maintainer: David S. Fulford
License: MIT License
Project-URL: Homepage, https://github.com/petbox-dev/combocurve-api-helper.git
Project-URL: Repository, https://github.com/petbox-dev/combocurve-api-helper.git
Project-URL: Issues, https://github.com/petbox-dev/combocurve-api-helper/issues
Keywords: combocurve-api-helper,combocurve,cc,api
Classifier: Development Status :: 5 - Production/Stable
Classifier: Intended Audience :: Science/Research
Classifier: Intended Audience :: Education
Classifier: Intended Audience :: Developers
Classifier: Natural Language :: English
Classifier: License :: OSI Approved :: MIT License
Classifier: Programming Language :: Python :: 3.8
Classifier: Programming Language :: Python :: 3.9
Classifier: Programming Language :: Python :: 3.10
Classifier: Programming Language :: Python :: 3.11
Classifier: Programming Language :: Python :: 3.12
Classifier: Programming Language :: Python :: 3.13
Classifier: Topic :: Scientific/Engineering
Classifier: Topic :: Scientific/Engineering :: Mathematics
Classifier: Topic :: Software Development :: Libraries
Classifier: Typing :: Typed
Requires-Python: >=3.8
License-File: LICENSE
Requires-Dist: combocurve-api-v1
Requires-Dist: more-itertools
Requires-Dist: requests
Requires-Dist: typing-extensions
Dynamic: license-file
